Metadata-Version: 2.1
Name: netas-xmla-with-dax
Version: 0.8.0.1
Summary: Access olap data sources through xmla
Home-page: https://github.com/may-day/olap
Author: Norman Krämer
Author-email: kraemer.norman@googlemail.com
License: Apache Software License 2.0
Platform: UNKNOWN
Classifier: License :: OSI Approved :: Apache Software License
Classifier: Programming Language :: Python :: 2
Classifier: Programming Language :: Python :: 3
Classifier: Development Status :: 3 - Alpha
Classifier: Environment :: Web Environment
Classifier: Intended Audience :: Developers
Classifier: Topic :: Software Development :: Libraries :: Python Modules
